{
  "created_at": "2025-05-03T14:32:32.609579+00:00",
  "elapsed": 0.190806,
  "encoding": "utf-8",
  "expires": "2025-05-04T14:32:32.609579+00:00",
  "headers": {
    "Access-Control-Allow-Methods": "POST, GET, OPTIONS",
    "Access-Control-Allow-Origin": "*",
    "Access-Control-Max-Age": "86400",
    "Alt-Svc": "h3=\":443\"; ma=2592000,h3-29=\":443\"; ma=2592000",
    "Content-Length": "1939",
    "Content-Type": "application\/json",
    "Date": "Sat, 03 May 2025 14:32:32 GMT",
    "Server": "openresty\/1.13.6.2",
    "Via": "1.1 google"
  },
  "reason": "OK",
  "request": {
    "body": "",
    "headers": {
      "Accept": "*\/*",
      "Accept-Encoding": "gzip, deflate, br, zstd",
      "Connection": "keep-alive",
      "User-Agent": "python-requests\/2.31.0"
    },
    "method": "GET",
    "url": "https:\/\/ws.audioscrobbler.com\/2.0\/?api_key=REDACTED&artist=PARTYNEXTDOOR&format=json&method=track.getInfo&track=The+News"
  },
  "status_code": 200,
  "url": "https:\/\/ws.audioscrobbler.com\/2.0\/?api_key=REDACTED&artist=PARTYNEXTDOOR&format=json&method=track.getInfo&track=The+News",
  "_decoded_content": {
    "track": {
      "name": "The News",
      "url": "https:\/\/www.last.fm\/music\/PARTYNEXTDOOR\/_\/The+News",
      "duration": "0",
      "streamable": {
        "#text": "0",
        "fulltrack": "0"
      },
      "listeners": "169673",
      "playcount": "1592255",
      "artist": {
        "name": "PARTYNEXTDOOR",
        "mbid": "f23ef341-33bd-47c1-b83c-846a78581f05",
        "url": "https:\/\/www.last.fm\/music\/PARTYNEXTDOOR"
      },
      "toptags": {
        "tag": [
          {
            "name": "downtempo",
            "url": "https:\/\/www.last.fm\/tag\/downtempo"
          },
          {
            "name": "trap",
            "url": "https:\/\/www.last.fm\/tag\/trap"
          },
          {
            "name": "alternative rnb",
            "url": "https:\/\/www.last.fm\/tag\/alternative+rnb"
          },
          {
            "name": "my top songs",
            "url": "https:\/\/www.last.fm\/tag\/my+top+songs"
          },
          {
            "name": "partynextdoor",
            "url": "https:\/\/www.last.fm\/tag\/partynextdoor"
          }
        ]
      },
      "wiki": {
        "published": "25 Nov 2019, 06:37",
        "summary": "\u201cThe News\u201d was released alongside \u2018'Loyal\u2019,' featuring Drake, on November 22nd, 2019. The songs are suspected to be the first two singles for PARTYNEXTDOOR\u2019s long awaited project, first mentioned in 2017, reportedly named Club Atlantis.\n\nOn the track, PND sings to his significant other, telling them that they don\u2019t deserve him, and seemingly implicating that they are cheating on him, or are at least not fully committed within the relationship. <a href=\"http:\/\/www.last.fm\/music\/PARTYNEXTDOOR\/_\/The+News\">Read more on Last.fm<\/a>.",
        "content": "\u201cThe News\u201d was released alongside \u2018'Loyal\u2019,' featuring Drake, on November 22nd, 2019. The songs are suspected to be the first two singles for PARTYNEXTDOOR\u2019s long awaited project, first mentioned in 2017, reportedly named Club Atlantis.\n\nOn the track, PND sings to his significant other, telling them that they don\u2019t deserve him, and seemingly implicating that they are cheating on him, or are at least not fully committed within the relationship. <a href=\"http:\/\/www.last.fm\/music\/PARTYNEXTDOOR\/_\/The+News\">Read more on Last.fm<\/a>. User-contributed text is available under the Creative Commons By-SA License; additional terms may apply."
      }
    }
  }
}