{
  "created_at": "2025-05-03T14:44:52.562638+00:00",
  "elapsed": 0.209315,
  "encoding": "utf-8",
  "expires": "2025-05-04T14:44:52.562638+00:00",
  "headers": {
    "Access-Control-Allow-Methods": "POST, GET, OPTIONS",
    "Access-Control-Allow-Origin": "*",
    "Access-Control-Max-Age": "86400",
    "Alt-Svc": "h3=\":443\"; ma=2592000,h3-29=\":443\"; ma=2592000",
    "Content-Length": "1853",
    "Content-Type": "application\/json",
    "Date": "Sat, 03 May 2025 14:44:52 GMT",
    "Server": "openresty\/1.13.6.2",
    "Via": "1.1 google"
  },
  "reason": "OK",
  "request": {
    "body": "",
    "headers": {
      "Accept": "*\/*",
      "Accept-Encoding": "gzip, deflate, br, zstd",
      "Connection": "keep-alive",
      "User-Agent": "python-requests\/2.31.0"
    },
    "method": "GET",
    "url": "https:\/\/ws.audioscrobbler.com\/2.0\/?api_key=REDACTED&artist=Little+Mix&format=json&method=track.getInfo&track=No+More+Sad+Songs"
  },
  "status_code": 200,
  "url": "https:\/\/ws.audioscrobbler.com\/2.0\/?api_key=REDACTED&artist=Little+Mix&format=json&method=track.getInfo&track=No+More+Sad+Songs",
  "_decoded_content": {
    "track": {
      "name": "No More Sad Songs",
      "url": "https:\/\/www.last.fm\/music\/Little+Mix\/_\/No+More+Sad+Songs",
      "duration": "206000",
      "streamable": {
        "#text": "0",
        "fulltrack": "0"
      },
      "listeners": "108056",
      "playcount": "1120108",
      "artist": {
        "name": "Little Mix",
        "mbid": "38f59974-2f4d-4bfa-b2e3-d2696de1b675",
        "url": "https:\/\/www.last.fm\/music\/Little+Mix"
      },
      "album": {
        "artist": "Little Mix",
        "title": "Glory Days (Deluxe)",
        "url": "https:\/\/www.last.fm\/music\/Little+Mix\/Glory+Days+(Deluxe)",
        "image": [
          {
            "#text": "https:\/\/lastfm.freetls.fastly.net\/i\/u\/34s\/cd68d1ca4c06e6364549852b7b4def27.png",
            "size": "small"
          },
          {
            "#text": "https:\/\/lastfm.freetls.fastly.net\/i\/u\/64s\/cd68d1ca4c06e6364549852b7b4def27.png",
            "size": "medium"
          },
          {
            "#text": "https:\/\/lastfm.freetls.fastly.net\/i\/u\/174s\/cd68d1ca4c06e6364549852b7b4def27.png",
            "size": "large"
          },
          {
            "#text": "https:\/\/lastfm.freetls.fastly.net\/i\/u\/300x300\/cd68d1ca4c06e6364549852b7b4def27.png",
            "size": "extralarge"
          }
        ]
      },
      "toptags": {
        "tag": [
          {
            "name": "pop",
            "url": "https:\/\/www.last.fm\/tag\/pop"
          },
          {
            "name": "best of 2016",
            "url": "https:\/\/www.last.fm\/tag\/best+of+2016"
          },
          {
            "name": "hino",
            "url": "https:\/\/www.last.fm\/tag\/hino"
          },
          {
            "name": "best of little mix",
            "url": "https:\/\/www.last.fm\/tag\/best+of+little+mix"
          },
          {
            "name": "inspirational",
            "url": "https:\/\/www.last.fm\/tag\/inspirational"
          }
        ]
      },
      "wiki": {
        "published": "17 Jan 2022, 04:14",
        "summary": "\"No More Sad Songs\" is a song by British girl group Little Mix, from the group's fourth studio album, Glory Days (2016). <a href=\"http:\/\/www.last.fm\/music\/Little+Mix\/_\/No+More+Sad+Songs\">Read more on Last.fm<\/a>.",
        "content": "\"No More Sad Songs\" is a song by British girl group Little Mix, from the group's fourth studio album, Glory Days (2016). <a href=\"http:\/\/www.last.fm\/music\/Little+Mix\/_\/No+More+Sad+Songs\">Read more on Last.fm<\/a>. User-contributed text is available under the Creative Commons By-SA License; additional terms may apply."
      }
    }
  }
}