{
  "created_at": "2025-05-03T14:44:16.214628+00:00",
  "elapsed": 0.211888,
  "encoding": "utf-8",
  "expires": "2025-05-04T14:44:16.214628+00:00",
  "headers": {
    "Access-Control-Allow-Methods": "POST, GET, OPTIONS",
    "Access-Control-Allow-Origin": "*",
    "Access-Control-Max-Age": "86400",
    "Alt-Svc": "h3=\":443\"; ma=2592000,h3-29=\":443\"; ma=2592000",
    "Content-Length": "1279",
    "Content-Type": "application\/json",
    "Date": "Sat, 03 May 2025 14:44:16 GMT",
    "Server": "openresty\/1.13.6.2",
    "Via": "1.1 google"
  },
  "reason": "OK",
  "request": {
    "body": "",
    "headers": {
      "Accept": "*\/*",
      "Accept-Encoding": "gzip, deflate, br, zstd",
      "Connection": "keep-alive",
      "User-Agent": "python-requests\/2.31.0"
    },
    "method": "GET",
    "url": "https:\/\/ws.audioscrobbler.com\/2.0\/?api_key=REDACTED&artist=Panic%21+At+The+Disco&format=json&method=track.getInfo&track=Hey+Look+Ma%2C+I+Made+It"
  },
  "status_code": 200,
  "url": "https:\/\/ws.audioscrobbler.com\/2.0\/?api_key=REDACTED&artist=Panic%21+At+The+Disco&format=json&method=track.getInfo&track=Hey+Look+Ma%2C+I+Made+It",
  "_decoded_content": {
    "track": {
      "name": "Hey Look Ma, I Made It",
      "url": "https:\/\/www.last.fm\/music\/Panic%21+at+the+Disco\/_\/Hey+Look+Ma,+I+Made+It",
      "duration": "169000",
      "streamable": {
        "#text": "0",
        "fulltrack": "0"
      },
      "listeners": "302397",
      "playcount": "2412495",
      "artist": {
        "name": "Panic! at the Disco",
        "mbid": "b9472588-93f3-4922-a1a2-74082cdf9ce8",
        "url": "https:\/\/www.last.fm\/music\/Panic%21+at+the+Disco"
      },
      "album": {
        "artist": "Various Artists",
        "title": "Songs to Make You Feel Good",
        "url": "https:\/\/www.last.fm\/music\/Various+Artists\/Songs+to+Make+You+Feel+Good",
        "image": [
          {
            "#text": "https:\/\/lastfm.freetls.fastly.net\/i\/u\/34s\/ebee7784f84161995f5283ec9382c660.png",
            "size": "small"
          },
          {
            "#text": "https:\/\/lastfm.freetls.fastly.net\/i\/u\/64s\/ebee7784f84161995f5283ec9382c660.png",
            "size": "medium"
          },
          {
            "#text": "https:\/\/lastfm.freetls.fastly.net\/i\/u\/174s\/ebee7784f84161995f5283ec9382c660.png",
            "size": "large"
          },
          {
            "#text": "https:\/\/lastfm.freetls.fastly.net\/i\/u\/300x300\/ebee7784f84161995f5283ec9382c660.png",
            "size": "extralarge"
          }
        ]
      },
      "toptags": {
        "tag": [
          {
            "name": "pop",
            "url": "https:\/\/www.last.fm\/tag\/pop"
          },
          {
            "name": "alternative",
            "url": "https:\/\/www.last.fm\/tag\/alternative"
          },
          {
            "name": "dance",
            "url": "https:\/\/www.last.fm\/tag\/dance"
          },
          {
            "name": "pop rock",
            "url": "https:\/\/www.last.fm\/tag\/pop+rock"
          },
          {
            "name": "2010s",
            "url": "https:\/\/www.last.fm\/tag\/2010s"
          }
        ]
      }
    }
  }
}