{
  "created_at": "2025-05-03T14:39:32.659528+00:00",
  "elapsed": 0.293226,
  "encoding": "utf-8",
  "expires": "2025-05-04T14:39:32.659528+00:00",
  "headers": {
    "Access-Control-Allow-Methods": "POST, GET, OPTIONS",
    "Access-Control-Allow-Origin": "*",
    "Access-Control-Max-Age": "86400",
    "Alt-Svc": "h3=\":443\"; ma=2592000,h3-29=\":443\"; ma=2592000",
    "Content-Length": "882",
    "Content-Type": "application\/json",
    "Date": "Sat, 03 May 2025 14:39:32 GMT",
    "Server": "openresty\/1.13.6.2",
    "Via": "1.1 google"
  },
  "reason": "OK",
  "request": {
    "body": "",
    "headers": {
      "Accept": "*\/*",
      "Accept-Encoding": "gzip, deflate, br, zstd",
      "Connection": "keep-alive",
      "User-Agent": "python-requests\/2.31.0"
    },
    "method": "GET",
    "url": "https:\/\/ws.audioscrobbler.com\/2.0\/?api_key=REDACTED&artist=Mrs.+Green+Apple&format=json&method=track.getInfo&track=Que+Sera+Sera"
  },
  "status_code": 200,
  "url": "https:\/\/ws.audioscrobbler.com\/2.0\/?api_key=REDACTED&artist=Mrs.+Green+Apple&format=json&method=track.getInfo&track=Que+Sera+Sera",
  "_decoded_content": {
    "track": {
      "name": "Que Sera Sera",
      "url": "https:\/\/www.last.fm\/music\/Mrs.+GREEN+APPLE\/_\/Que+Sera+Sera",
      "duration": "272000",
      "streamable": {
        "#text": "0",
        "fulltrack": "0"
      },
      "listeners": "968",
      "playcount": "3727",
      "artist": {
        "name": "Mrs. GREEN APPLE",
        "url": "https:\/\/www.last.fm\/music\/Mrs.+GREEN+APPLE"
      },
      "album": {
        "artist": "Mrs. GREEN APPLE",
        "title": "Que Sera Sera",
        "url": "https:\/\/www.last.fm\/music\/Mrs.+GREEN+APPLE\/Que+Sera+Sera",
        "image": [
          {
            "#text": "https:\/\/lastfm.freetls.fastly.net\/i\/u\/34s\/d37a4447fd8ab3db0ceb19019c7a233a.png",
            "size": "small"
          },
          {
            "#text": "https:\/\/lastfm.freetls.fastly.net\/i\/u\/64s\/d37a4447fd8ab3db0ceb19019c7a233a.png",
            "size": "medium"
          },
          {
            "#text": "https:\/\/lastfm.freetls.fastly.net\/i\/u\/174s\/d37a4447fd8ab3db0ceb19019c7a233a.png",
            "size": "large"
          },
          {
            "#text": "https:\/\/lastfm.freetls.fastly.net\/i\/u\/300x300\/d37a4447fd8ab3db0ceb19019c7a233a.png",
            "size": "extralarge"
          }
        ]
      },
      "toptags": {
        "tag": []
      }
    }
  }
}