{
  "created_at": "2025-05-03T14:35:44.877511+00:00",
  "elapsed": 0.218095,
  "encoding": "utf-8",
  "expires": "2025-05-04T14:35:44.877511+00:00",
  "headers": {
    "Access-Control-Allow-Methods": "POST, GET, OPTIONS",
    "Access-Control-Allow-Origin": "*",
    "Access-Control-Max-Age": "86400",
    "Alt-Svc": "h3=\":443\"; ma=2592000,h3-29=\":443\"; ma=2592000",
    "Content-Length": "821",
    "Content-Type": "application\/json",
    "Date": "Sat, 03 May 2025 14:35:45 GMT",
    "Server": "openresty\/1.13.6.2",
    "Via": "1.1 google"
  },
  "reason": "OK",
  "request": {
    "body": "",
    "headers": {
      "Accept": "*\/*",
      "Accept-Encoding": "gzip, deflate, br, zstd",
      "Connection": "keep-alive",
      "User-Agent": "python-requests\/2.31.0"
    },
    "method": "GET",
    "url": "https:\/\/ws.audioscrobbler.com\/2.0\/?api_key=REDACTED&artist=Morat&format=json&method=track.getInfo&track=Idiota"
  },
  "status_code": 200,
  "url": "https:\/\/ws.audioscrobbler.com\/2.0\/?api_key=REDACTED&artist=Morat&format=json&method=track.getInfo&track=Idiota",
  "_decoded_content": {
    "track": {
      "name": "Idiota",
      "url": "https:\/\/www.last.fm\/music\/Morat\/_\/Idiota",
      "duration": "184000",
      "streamable": {
        "#text": "0",
        "fulltrack": "0"
      },
      "listeners": "39906",
      "playcount": "428822",
      "artist": {
        "name": "Morat",
        "url": "https:\/\/www.last.fm\/music\/Morat"
      },
      "album": {
        "artist": "Morat",
        "title": "Canta con MORAT",
        "url": "https:\/\/www.last.fm\/music\/Morat\/Canta+con+MORAT",
        "image": [
          {
            "#text": "https:\/\/lastfm.freetls.fastly.net\/i\/u\/34s\/c351d4573a36ecfd6496f8aa824179b5.png",
            "size": "small"
          },
          {
            "#text": "https:\/\/lastfm.freetls.fastly.net\/i\/u\/64s\/c351d4573a36ecfd6496f8aa824179b5.png",
            "size": "medium"
          },
          {
            "#text": "https:\/\/lastfm.freetls.fastly.net\/i\/u\/174s\/c351d4573a36ecfd6496f8aa824179b5.png",
            "size": "large"
          },
          {
            "#text": "https:\/\/lastfm.freetls.fastly.net\/i\/u\/300x300\/c351d4573a36ecfd6496f8aa824179b5.png",
            "size": "extralarge"
          }
        ]
      },
      "toptags": {
        "tag": []
      }
    }
  }
}